yjs_widgets/__init__.py
yjs_widgets/_version.py
yjs_widgets-0.4.0.data/data/share/jupyter/labextensions/yjs-widgets/package.json
yjs_widgets-0.4.0.data/data/share/jupyter/labextensions/yjs-widgets/static/353.8bd06984fd046b4482d0.js
yjs_widgets-0.4.0.data/data/share/jupyter/labextensions/yjs-widgets/static/728.ce7809c06d361f158130.js
yjs_widgets-0.4.0.data/data/share/jupyter/labextensions/yjs-widgets/static/737.c0c4f6b4f62a356ae6e0.js
yjs_widgets-0.4.0.data/data/share/jupyter/labextensions/yjs-widgets/static/remoteEntry.31594e161cbb51e2ccf9.js
yjs_widgets-0.4.0.data/data/share/jupyter/labextensions/yjs-widgets/static/style.js
yjs_widgets-0.4.0.data/data/share/jupyter/labextensions/yjs-widgets/static/third-party-licenses.json
yjs_widgets-0.4.0.data/data/share/jupyter/labextensions/yjs-widgets/install.json
yjs_widgets-0.4.0.dist-info/METADATA
yjs_widgets-0.4.0.dist-info/WHEEL
yjs_widgets-0.4.0.dist-info/licenses/LICENSE
yjs_widgets-0.4.0.dist-info/RECORD
