Metadata-Version: 2.4
Name: yjs-widgets
Version: 0.4.0
Dynamic: Keywords
Summary: A JupyterLab extension for widgets based on Yjs.
Project-URL: Homepage, https://github.com/QuantStack/yjs-widgets
Project-URL: Bug Tracker, https://github.com/QuantStack/yjs-widgets/issues
Project-URL: Repository, https://github.com/QuantStack/yjs-widgets.git
Author-email: Trung Le <leductrungxf@gmail.com>
License: BSD 3-Clause License
License-File: LICENSE
Classifier: Framework :: Jupyter
Classifier: Framework :: Jupyter :: JupyterLab
Classifier: Framework :: Jupyter :: JupyterLab :: 3
Classifier: Framework :: Jupyter :: JupyterLab :: Extensions
Classifier: Framework :: Jupyter :: JupyterLab :: Extensions :: Prebuilt
Classifier: License :: OSI Approved :: BSD License
Classifier: Programming Language :: Python
Classifier: Programming Language :: Python :: 3
Classifier: Programming Language :: Python :: 3.7
Classifier: Programming Language :: Python :: 3.8
Classifier: Programming Language :: Python :: 3.9
Classifier: Programming Language :: Python :: 3.10
Classifier: Programming Language :: Python :: 3.11
Requires-Python: >=3.7
